qtme/__init__.py
qtme-0.1.dev0.dist-info/AUTHORS
qtme-0.1.dev0.dist-info/LICENSE
qtme-0.1.dev0.dist-info/METADATA
qtme-0.1.dev0.dist-info/WHEEL
qtme-0.1.dev0.dist-info/top_level.txt
qtme-0.1.dev0.dist-info/RECORD
