Metadata-Version: 2.1
Name: qtme
Version: 0.1.dev0
Summary: Multimedia editor for PyQt/PySide
Home-page: http://www.jdhp.org/software_en.html#qtme
Download-URL: http://www.jdhp.org/software_en.html#qtme
Author: Jérémie DECOCK
Author-email: jd.jdhp@gmail.com
Maintainer: Jérémie DECOCK
Maintainer-email: jd.jdhp@gmail.com
Project-URL: Bug Tracker, https://gitlab.com/jdhp/qt-multimedia-editor/issues
Keywords: qtme
Classifier: Development Status :: 4 - Beta
Classifier: Intended Audience :: Developers
Classifier: Natural Language :: English
Classifier: Operating System :: OS Independent
Classifier: Programming Language :: Python :: 3
Classifier: Topic :: Software Development :: Libraries
Classifier: Topic :: Software Development :: Libraries :: Python Modules
Classifier: Topic :: Software Development :: Libraries :: Application Frameworks
Requires-Python: >=3.9
License-File: LICENSE
License-File: AUTHORS
